<?xml version="1.0" encoding="utf-8"?>
<clothing-items>
 <clothing>
  <id>
   962274400
  </id>
  <name>
   Ellesse Belts F-1638
  </name>
  <category>
   Belts
  </category>
  <size>
   XL
  </size>
  <color>
   Красный
  </color>
  <material>
   Вискоза
  </material>
  <price>
   451393
  </price>
  <rating>
   2.09
  </rating>
  <reviews>
   804028
  </reviews>
  <new>
   +
  </new>
  <exclusive>
   no
  </exclusive>
 </clothing>
 <clothing>
  <id>
   735391709
  </id>
  <name>
   Fila T-shirt M-1221
  </name>
  <category>
   T-shirt
  </category>
  <size>
   S
  </size>
  <color>
   Желтый
  </color>
  <material>
   Хлопок
  </material>
  <price>
   508522
  </price>
  <rating>
   2.23
  </rating>
  <reviews>
   480177
  </reviews>
  <new>
   -
  </new>
  <exclusive>
   no
  </exclusive>
 </clothing>
 <clothing>
  <id>
   792954473
  </id>
  <name>
   Vans Hat H-6912
  </name>
  <category>
   Hat
  </category>
  <size>
   XXL
  </size>
  <color>
   Красный
  </color>
  <material>
   Нейлон
  </material>
  <price>
   727526
  </price>
  <rating>
   1.64
  </rating>
  <reviews>
   67971
  </reviews>
  <new>
   -
  </new>
  <exclusive>
   no
  </exclusive>
 </clothing>
 <clothing>
  <id>
   754773934
  </id>
  <name>
   New Balance Jacket F-8404
  </name>
  <category>
   Jacket
  </category>
  <size>
   S
  </size>
  <color>
   Синий
  </color>
  <material>
   Шерсть
  </material>
  <price>
   893548
  </price>
  <rating>
   1.61
  </rating>
  <reviews>
   390634
  </reviews>
  <new>
   +
  </new>
  <exclusive>
   yes
  </exclusive>
  <sporty>
   no
  </sporty>
 </clothing>
 <clothing>
  <id>
   914191629
  </id>
  <name>
   Adidas Jeans V-5985
  </name>
  <category>
   Jeans
  </category>
  <size>
   M
  </size>
  <color>
   Желтый
  </color>
  <material>
   Лен
  </material>
  <price>
   341757
  </price>
  <rating>
   3.57
  </rating>
  <reviews>
   960512
  </reviews>
  <new>
   +
  </new>
  <exclusive>
   no
  </exclusive>
  <sporty>
   no
  </sporty>
 </clothing>
 <clothing>
  <id>
   873868778
  </id>
  <name>
   Nike Pants T-5965
  </name>
  <category>
   Pants
  </category>
  <size>
   XL
  </size>
  <color>
   Оранжевый
  </color>
  <material>
   Полиэстер
  </material>
  <price>
   644134
  </price>
  <rating>
   4.54
  </rating>
  <reviews>
   608632
  </reviews>
  <new>
   -
  </new>
  <exclusive>
   no
  </exclusive>
 </clothing>
 <clothing>
  <id>
   614479557
  </id>
  <name>
   Lacoste Hat Q-4990
  </name>
  <category>
   Hat
  </category>
  <size>
   XL
  </size>
  <color>
   Красный
  </color>
  <material>
   Шерсть
  </material>
  <price>
   960637
  </price>
  <rating>
   2.65
  </rating>
  <reviews>
   912475
  </reviews>
  <new>
   -
  </new>
  <sporty>
   yes
  </sporty>
 </clothing>
 <clothing>
  <id>
   490236082
  </id>
  <name>
   Asics Skirt F-7612
  </name>
  <category>
   Skirt
  </category>
  <size>
   XXL
  </size>
  <color>
   Зеленый
  </color>
  <material>
   Шелк
  </material>
  <price>
   442354
  </price>
  <rating>
   4.3
  </rating>
  <reviews>
   453709
  </reviews>
  <new>
   +
  </new>
 </clothing>
 <clothing>
  <id>
   500041073
  </id>
  <name>
   Vans Blouse Y-4741
  </name>
  <category>
   Blouse
  </category>
  <size>
   M
  </size>
  <color>
   Красный
  </color>
  <material>
   Вискоза
  </material>
  <price>
   486840
  </price>
  <rating>
   3.64
  </rating>
  <reviews>
   388125
  </reviews>
  <exclusive>
   no
  </exclusive>
  <sporty>
   no
  </sporty>
 </clothing>
 <clothing>
  <id>
   283421845
  </id>
  <name>
   Nike Jacket J-5612
  </name>
  <category>
   Jacket
  </category>
  <size>
   XL
  </size>
  <color>
   Голубой
  </color>
  <material>
   Полиэстер
  </material>
  <price>
   361110
  </price>
  <rating>
   3.47
  </rating>
  <reviews>
   218715
  </reviews>
  <exclusive>
   no
  </exclusive>
 </clothing>
 <clothing>
  <id>
   392114142
  </id>
  <name>
   DC Dress N-8327
  </name>
  <category>
   Dress
  </category>
  <size>
   S
  </size>
  <color>
   Фиолетовый
  </color>
  <material>
   Нейлон
  </material>
  <price>
   149863
  </price>
  <rating>
   1.82
  </rating>
  <reviews>
   923052
  </reviews>
  <new>
   -
  </new>
  <sporty>
   yes
  </sporty>
 </clothing>
 <clothing>
  <id>
   147764864
  </id>
  <name>
   Adidas Jacket F-4600
  </name>
  <category>
   Jacket
  </category>
  <size>
   XL
  </size>
  <color>
   Красный
  </color>
  <material>
   Кожа
  </material>
  <price>
   500969
  </price>
  <rating>
   2.01
  </rating>
  <reviews>
   444127
  </reviews>
  <exclusive>
   no
  </exclusive>
 </clothing>
 <clothing>
  <id>
   694766635
  </id>
  <name>
   Adidas Sweater V-4607
  </name>
  <category>
   Sweater
  </category>
  <size>
   M
  </size>
  <color>
   Красный
  </color>
  <material>
   Кожа
  </material>
  <price>
   221724
  </price>
  <rating>
   2.71
  </rating>
  <reviews>
   26048
  </reviews>
  <new>
   -
  </new>
 </clothing>
 <clothing>
  <id>
   862423196
  </id>
  <name>
   Adidas Dress A-7204
  </name>
  <category>
   Dress
  </category>
  <size>
   XXL
  </size>
  <color>
   Желтый
  </color>
  <material>
   Шерсть
  </material>
  <price>
   501478
  </price>
  <rating>
   1.31
  </rating>
  <reviews>
   400851
  </reviews>
  <exclusive>
   no
  </exclusive>
 </clothing>
 <clothing>
  <id>
   362026110
  </id>
  <name>
   Asics Shoes Q-8829
  </name>
  <category>
   Shoes
  </category>
  <size>
   M
  </size>
  <color>
   Красный
  </color>
  <material>
   Хлопок
  </material>
  <price>
   642102
  </price>
  <rating>
   4.39
  </rating>
  <reviews>
   490493
  </reviews>
  <sporty>
   no
  </sporty>
 </clothing>
 <clothing>
  <id>
   123838380
  </id>
  <name>
   Fila Umbrellas O-6922
  </name>
  <category>
   Umbrellas
  </category>
  <size>
   L
  </size>
  <color>
   Голубой
  </color>
  <material>
   Лен
  </material>
  <price>
   801276
  </price>
  <rating>
   1.67
  </rating>
  <reviews>
   424115
  </reviews>
  <new>
   -
  </new>
  <sporty>
   yes
  </sporty>
 </clothing>
 <clothing>
  <id>
   214292660
  </id>
  <name>
   DC Belts R-6663
  </name>
  <category>
   Belts
  </category>
  <size>
   XL
  </size>
  <color>
   Зеленый
  </color>
  <material>
   Кожа
  </material>
  <price>
   881013
  </price>
  <rating>
   2.37
  </rating>
  <reviews>
   113461
  </reviews>
  <sporty>
   yes
  </sporty>
 </clothing>
 <clothing>
  <id>
   509282511
  </id>
  <name>
   Under Armour Shirt G-3624
  </name>
  <category>
   Shirt
  </category>
  <size>
   XXL
  </size>
  <color>
   Зеленый
  </color>
  <material>
   Шелк
  </material>
  <price>
   122958
  </price>
  <rating>
   2.75
  </rating>
  <reviews>
   116936
  </reviews>
  <sporty>
   no
  </sporty>
 </clothing>
 <clothing>
  <id>
   789745671
  </id>
  <name>
   Puma Gloves Z-5078
  </name>
  <category>
   Gloves
  </category>
  <size>
   S
  </size>
  <color>
   Фиолетовый
  </color>
  <material>
   Полиэстер
  </material>
  <price>
   507481
  </price>
  <rating>
   2.32
  </rating>
  <reviews>
   894495
  </reviews>
  <new>
   +
  </new>
  <exclusive>
   no
  </exclusive>
  <sporty>
   no
  </sporty>
 </clothing>
 <clothing>
  <id>
   332141712
  </id>
  <name>
   PleinSport Skirt W-1520
  </name>
  <category>
   Skirt
  </category>
  <size>
   M
  </size>
  <color>
   Желтый
  </color>
  <material>
   Полиэстер
  </material>
  <price>
   409650
  </price>
  <rating>
   4.69
  </rating>
  <reviews>
   125748
  </reviews>
  <new>
   -
  </new>
 </clothing>
 <clothing>
  <id>
   811624685
  </id>
  <name>
   Asics Hat S-4890
  </name>
  <category>
   Hat
  </category>
  <size>
   XXL
  </size>
  <color>
   Фиолетовый
  </color>
  <material>
   Вискоза
  </material>
  <price>
   957886
  </price>
  <rating>
   2.59
  </rating>
  <reviews>
   662736
  </reviews>
 </clothing>
 <clothing>
  <id>
   337375853
  </id>
  <name>
   Asics Shoes L-3433
  </name>
  <category>
   Shoes
  </category>
  <size>
   XL
  </size>
  <color>
   Зеленый
  </color>
  <material>
   Полиэстер
  </material>
  <price>
   763517
  </price>
  <rating>
   4.55
  </rating>
  <reviews>
   133038
  </reviews>
  <new>
   -
  </new>
  <sporty>
   no
  </sporty>
 </clothing>
 <clothing>
  <id>
   981314368
  </id>
  <name>
   Addidas Dress R-1202
  </name>
  <category>
   Dress
  </category>
  <size>
   XL
  </size>
  <color>
   Зеленый
  </color>
  <material>
   Кожа
  </material>
  <price>
   915924
  </price>
  <rating>
   1.63
  </rating>
  <reviews>
   116976
  </reviews>
  <new>
   +
  </new>
  <exclusive>
   yes
  </exclusive>
  <sporty>
   no
  </sporty>
 </clothing>
 <clothing>
  <id>
   634569809
  </id>
  <name>
   Ellesse Umbrellas A-2497
  </name>
  <category>
   Umbrellas
  </category>
  <size>
   S
  </size>
  <color>
   Желтый
  </color>
  <material>
   Хлопок
  </material>
  <price>
   244311
  </price>
  <rating>
   1.34
  </rating>
  <reviews>
   576792
  </reviews>
  <exclusive>
   yes
  </exclusive>
  <sporty>
   no
  </sporty>
 </clothing>
 <clothing>
  <id>
   282748405
  </id>
  <name>
   Puma Socks N-8526
  </name>
  <category>
   Socks
  </category>
  <size>
   XXL
  </size>
  <color>
   Оранжевый
  </color>
  <material>
   Кожа
  </material>
  <price>
   201842
  </price>
  <rating>
   2.35
  </rating>
  <reviews>
   152159
  </reviews>
  <exclusive>
   yes
  </exclusive>
 </clothing>
 <clothing>
  <id>
   260897595
  </id>
  <name>
   Converse Handbags X-4167
  </name>
  <category>
   Handbags
  </category>
  <size>
   XL
  </size>
  <color>
   Голубой
  </color>
  <material>
   Нейлон
  </material>
  <price>
   299933
  </price>
  <rating>
   2.61
  </rating>
  <reviews>
   785108
  </reviews>
  <sporty>
   yes
  </sporty>
 </clothing>
 <clothing>
  <id>
   761404698
  </id>
  <name>
   New Balance T-shirt Z-5316
  </name>
  <category>
   T-shirt
  </category>
  <size>
   XXL
  </size>
  <color>
   Фиолетовый
  </color>
  <material>
   Полиэстер
  </material>
  <price>
   694279
  </price>
  <rating>
   1.76
  </rating>
  <reviews>
   725693
  </reviews>
  <new>
   -
  </new>
 </clothing>
 <clothing>
  <id>
   353650200
  </id>
  <name>
   Lacoste Dress I-8563
  </name>
  <category>
   Dress
  </category>
  <size>
   XXL
  </size>
  <color>
   Голубой
  </color>
  <material>
   Вискоза
  </material>
  <price>
   207012
  </price>
  <rating>
   3.17
  </rating>
  <reviews>
   411175
  </reviews>
  <exclusive>
   yes
  </exclusive>
 </clothing>
 <clothing>
  <id>
   874288642
  </id>
  <name>
   PleinSport T-shirt J-1218
  </name>
  <category>
   T-shirt
  </category>
  <size>
   L
  </size>
  <color>
   Синий
  </color>
  <material>
   Шелк
  </material>
  <price>
   617987
  </price>
  <rating>
   2.02
  </rating>
  <reviews>
   735466
  </reviews>
  <exclusive>
   no
  </exclusive>
  <sporty>
   yes
  </sporty>
 </clothing>
 <clothing>
  <id>
   308248287
  </id>
  <name>
   Lacoste Shirt I-9750
  </name>
  <category>
   Shirt
  </category>
  <size>
   L
  </size>
  <color>
   Зеленый
  </color>
  <material>
   Кожа
  </material>
  <price>
   985208
  </price>
  <rating>
   3.36
  </rating>
  <reviews>
   912719
  </reviews>
  <exclusive>
   no
  </exclusive>
  <sporty>
   yes
  </sporty>
 </clothing>
 <clothing>
  <id>
   375879632
  </id>
  <name>
   Asics Gloves Q-3376
  </name>
  <category>
   Gloves
  </category>
  <size>
   S
  </size>
  <color>
   Желтый
  </color>
  <material>
   Лен
  </material>
  <price>
   341056
  </price>
  <rating>
   2.53
  </rating>
  <reviews>
   831118
  </reviews>
  <exclusive>
   no
  </exclusive>
  <sporty>
   yes
  </sporty>
 </clothing>
 <clothing>
  <id>
   784559528
  </id>
  <name>
   Ellesse Umbrellas J-8113
  </name>
  <category>
   Umbrellas
  </category>
  <size>
   L
  </size>
  <color>
   Голубой
  </color>
  <material>
   Шерсть
  </material>
  <price>
   845186
  </price>
  <rating>
   3.2
  </rating>
  <reviews>
   531917
  </reviews>
  <sporty>
   no
  </sporty>
 </clothing>
 <clothing>
  <id>
   535037706
  </id>
  <name>
   DC Gloves F-3507
  </name>
  <category>
   Gloves
  </category>
  <size>
   M
  </size>
  <color>
   Желтый
  </color>
  <material>
   Хлопок
  </material>
  <price>
   155911
  </price>
  <rating>
   3.42
  </rating>
  <reviews>
   996548
  </reviews>
  <new>
   +
  </new>
  <exclusive>
   no
  </exclusive>
 </clothing>
 <clothing>
  <id>
   576232618
  </id>
  <name>
   DC Pants G-6340
  </name>
  <category>
   Pants
  </category>
  <size>
   XL
  </size>
  <color>
   Оранжевый
  </color>
  <material>
   Лен
  </material>
  <price>
   328078
  </price>
  <rating>
   4.67
  </rating>
  <reviews>
   144852
  </reviews>
  <new>
   -
  </new>
  <exclusive>
   no
  </exclusive>
  <sporty>
   no
  </sporty>
 </clothing>
 <clothing>
  <id>
   234737928
  </id>
  <name>
   Addidas Hat P-7993
  </name>
  <category>
   Hat
  </category>
  <size>
   S
  </size>
  <color>
   Голубой
  </color>
  <material>
   Лен
  </material>
  <price>
   681918
  </price>
  <rating>
   2.48
  </rating>
  <reviews>
   387329
  </reviews>
  <new>
   -
  </new>
  <sporty>
   no
  </sporty>
 </clothing>
 <clothing>
  <id>
   609140153
  </id>
  <name>
   Converse Jeans N-8819
  </name>
  <category>
   Jeans
  </category>
  <size>
   S
  </size>
  <color>
   Красный
  </color>
  <material>
   Шелк
  </material>
  <price>
   842702
  </price>
  <rating>
   1.85
  </rating>
  <reviews>
   673811
  </reviews>
  <new>
   -
  </new>
  <exclusive>
   no
  </exclusive>
 </clothing>
 <clothing>
  <id>
   645484119
  </id>
  <name>
   Vans Pants O-2520
  </name>
  <category>
   Pants
  </category>
  <size>
   XXL
  </size>
  <color>
   Желтый
  </color>
  <material>
   Лен
  </material>
  <price>
   474263
  </price>
  <rating>
   2.53
  </rating>
  <reviews>
   628648
  </reviews>
  <exclusive>
   yes
  </exclusive>
  <sporty>
   no
  </sporty>
 </clothing>
 <clothing>
  <id>
   868578321
  </id>
  <name>
   PleinSport Dress X-3271
  </name>
  <category>
   Dress
  </category>
  <size>
   M
  </size>
  <color>
   Красный
  </color>
  <material>
   Лен
  </material>
  <price>
   150131
  </price>
  <rating>
   3.45
  </rating>
  <reviews>
   325830
  </reviews>
  <new>
   +
  </new>
  <exclusive>
   yes
  </exclusive>
 </clothing>
 <clothing>
  <id>
   662612998
  </id>
  <name>
   Under Armour Shirt A-9515
  </name>
  <category>
   Shirt
  </category>
  <size>
   XXL
  </size>
  <color>
   Синий
  </color>
  <material>
   Полиэстер
  </material>
  <price>
   414429
  </price>
  <rating>
   4.2
  </rating>
  <reviews>
   539934
  </reviews>
  <exclusive>
   no
  </exclusive>
  <sporty>
   yes
  </sporty>
 </clothing>
 <clothing>
  <id>
   183293039
  </id>
  <name>
   Lacoste Sweater Y-2909
  </name>
  <category>
   Sweater
  </category>
  <size>
   L
  </size>
  <color>
   Фиолетовый
  </color>
  <material>
   Кожа
  </material>
  <price>
   411232
  </price>
  <rating>
   3.49
  </rating>
  <reviews>
   676565
  </reviews>
  <new>
   +
  </new>
  <exclusive>
   yes
  </exclusive>
 </clothing>
 <clothing>
  <id>
   405899442
  </id>
  <name>
   Brooks Socks U-7737
  </name>
  <category>
   Socks
  </category>
  <size>
   M
  </size>
  <color>
   Желтый
  </color>
  <material>
   Лен
  </material>
  <price>
   388941
  </price>
  <rating>
   3.63
  </rating>
  <reviews>
   385354
  </reviews>
  <new>
   -
  </new>
  <exclusive>
   yes
  </exclusive>
  <sporty>
   yes
  </sporty>
 </clothing>
 <clothing>
  <id>
   772164872
  </id>
  <name>
   Puma Belts E-3162
  </name>
  <category>
   Belts
  </category>
  <size>
   XXL
  </size>
  <color>
   Голубой
  </color>
  <material>
   Шерсть
  </material>
  <price>
   250280
  </price>
  <rating>
   2.36
  </rating>
  <reviews>
   313521
  </reviews>
  <new>
   -
  </new>
  <sporty>
   no
  </sporty>
 </clothing>
 <clothing>
  <id>
   900214416
  </id>
  <name>
   Reebok Gloves T-5669
  </name>
  <category>
   Gloves
  </category>
  <size>
   XXL
  </size>
  <color>
   Синий
  </color>
  <material>
   Полиэстер
  </material>
  <price>
   482813
  </price>
  <rating>
   2.91
  </rating>
  <reviews>
   610213
  </reviews>
  <new>
   -
  </new>
  <exclusive>
   no
  </exclusive>
 </clothing>
 <clothing>
  <id>
   892682001
  </id>
  <name>
   Asics Belts F-6839
  </name>
  <category>
   Belts
  </category>
  <size>
   L
  </size>
  <color>
   Фиолетовый
  </color>
  <material>
   Кожа
  </material>
  <price>
   762925
  </price>
  <rating>
   3.09
  </rating>
  <reviews>
   883051
  </reviews>
 </clothing>
 <clothing>
  <id>
   670928777
  </id>
  <name>
   Converse Hat J-1425
  </name>
  <category>
   Hat
  </category>
  <size>
   L
  </size>
  <color>
   Желтый
  </color>
  <material>
   Шелк
  </material>
  <price>
   811396
  </price>
  <rating>
   2.9
  </rating>
  <reviews>
   742904
  </reviews>
  <new>
   +
  </new>
  <sporty>
   no
  </sporty>
 </clothing>
 <clothing>
  <id>
   677246083
  </id>
  <name>
   Converse Handbags S-5237
  </name>
  <category>
   Handbags
  </category>
  <size>
   M
  </size>
  <color>
   Фиолетовый
  </color>
  <material>
   Вискоза
  </material>
  <price>
   715507
  </price>
  <rating>
   2.72
  </rating>
  <reviews>
   70671
  </reviews>
  <exclusive>
   no
  </exclusive>
 </clothing>
 <clothing>
  <id>
   642164139
  </id>
  <name>
   PleinSport Shirt L-4367
  </name>
  <category>
   Shirt
  </category>
  <size>
   XXL
  </size>
  <color>
   Красный
  </color>
  <material>
   Полиэстер
  </material>
  <price>
   757896
  </price>
  <rating>
   4.63
  </rating>
  <reviews>
   84679
  </reviews>
  <exclusive>
   yes
  </exclusive>
 </clothing>
 <clothing>
  <id>
   791332636
  </id>
  <name>
   Nike Hat A-3341
  </name>
  <category>
   Hat
  </category>
  <size>
   L
  </size>
  <color>
   Желтый
  </color>
  <material>
   Нейлон
  </material>
  <price>
   256977
  </price>
  <rating>
   2.08
  </rating>
  <reviews>
   452312
  </reviews>
  <sporty>
   yes
  </sporty>
 </clothing>
 <clothing>
  <id>
   699236701
  </id>
  <name>
   Puma Shoes J-3169
  </name>
  <category>
   Shoes
  </category>
  <size>
   XL
  </size>
  <color>
   Голубой
  </color>
  <material>
   Шерсть
  </material>
  <price>
   159082
  </price>
  <rating>
   3.68
  </rating>
  <reviews>
   844734
  </reviews>
  <new>
   +
  </new>
  <exclusive>
   yes
  </exclusive>
  <sporty>
   no
  </sporty>
 </clothing>
</clothing-items>
