<?xml version="1.0" encoding="utf-8"?>
<clothing-items>
 <clothing>
  <id>
   835284704
  </id>
  <name>
   Under Armour Blouse Z-5388
  </name>
  <category>
   Blouse
  </category>
  <size>
   XXL
  </size>
  <color>
   Зеленый
  </color>
  <material>
   Лен
  </material>
  <price>
   496357
  </price>
  <rating>
   4.22
  </rating>
  <reviews>
   430852
  </reviews>
  <exclusive>
   no
  </exclusive>
 </clothing>
 <clothing>
  <id>
   657637416
  </id>
  <name>
   Ellesse Handbags T-9905
  </name>
  <category>
   Handbags
  </category>
  <size>
   L
  </size>
  <color>
   Синий
  </color>
  <material>
   Вискоза
  </material>
  <price>
   195082
  </price>
  <rating>
   2.05
  </rating>
  <reviews>
   377010
  </reviews>
  <new>
   -
  </new>
 </clothing>
 <clothing>
  <id>
   239114420
  </id>
  <name>
   DC Umbrellas A-9046
  </name>
  <category>
   Umbrellas
  </category>
  <size>
   S
  </size>
  <color>
   Голубой
  </color>
  <material>
   Лен
  </material>
  <price>
   995179
  </price>
  <rating>
   3.47
  </rating>
  <reviews>
   853836
  </reviews>
  <new>
   -
  </new>
 </clothing>
 <clothing>
  <id>
   741382145
  </id>
  <name>
   Ellesse Jeans U-1433
  </name>
  <category>
   Jeans
  </category>
  <size>
   L
  </size>
  <color>
   Зеленый
  </color>
  <material>
   Шелк
  </material>
  <price>
   206156
  </price>
  <rating>
   4.76
  </rating>
  <reviews>
   653696
  </reviews>
  <new>
   +
  </new>
  <sporty>
   yes
  </sporty>
 </clothing>
 <clothing>
  <id>
   720845946
  </id>
  <name>
   PleinSport Gloves B-5336
  </name>
  <category>
   Gloves
  </category>
  <size>
   L
  </size>
  <color>
   Желтый
  </color>
  <material>
   Лен
  </material>
  <price>
   284952
  </price>
  <rating>
   2.15
  </rating>
  <reviews>
   878399
  </reviews>
  <new>
   -
  </new>
 </clothing>
 <clothing>
  <id>
   127743250
  </id>
  <name>
   Adidas Umbrellas I-9089
  </name>
  <category>
   Umbrellas
  </category>
  <size>
   M
  </size>
  <color>
   Желтый
  </color>
  <material>
   Лен
  </material>
  <price>
   923750
  </price>
  <rating>
   2.47
  </rating>
  <reviews>
   853488
  </reviews>
  <new>
   -
  </new>
  <exclusive>
   no
  </exclusive>
 </clothing>
 <clothing>
  <id>
   289016771
  </id>
  <name>
   Fila T-shirt E-9094
  </name>
  <category>
   T-shirt
  </category>
  <size>
   XL
  </size>
  <color>
   Голубой
  </color>
  <material>
   Лен
  </material>
  <price>
   129050
  </price>
  <rating>
   2.89
  </rating>
  <reviews>
   34991
  </reviews>
  <exclusive>
   no
  </exclusive>
 </clothing>
 <clothing>
  <id>
   782523085
  </id>
  <name>
   Lacoste Blouse W-9196
  </name>
  <category>
   Blouse
  </category>
  <size>
   S
  </size>
  <color>
   Красный
  </color>
  <material>
   Шерсть
  </material>
  <price>
   199215
  </price>
  <rating>
   4.67
  </rating>
  <reviews>
   833278
  </reviews>
  <new>
   -
  </new>
  <sporty>
   yes
  </sporty>
 </clothing>
 <clothing>
  <id>
   552246393
  </id>
  <name>
   Under Armour Socks B-3189
  </name>
  <category>
   Socks
  </category>
  <size>
   XXL
  </size>
  <color>
   Голубой
  </color>
  <material>
   Полиэстер
  </material>
  <price>
   798430
  </price>
  <rating>
   3.98
  </rating>
  <reviews>
   176851
  </reviews>
  <new>
   +
  </new>
  <exclusive>
   yes
  </exclusive>
 </clothing>
 <clothing>
  <id>
   624959445
  </id>
  <name>
   Vans Hat R-3836
  </name>
  <category>
   Hat
  </category>
  <size>
   M
  </size>
  <color>
   Голубой
  </color>
  <material>
   Лен
  </material>
  <price>
   606808
  </price>
  <rating>
   4.25
  </rating>
  <reviews>
   98366
  </reviews>
 </clothing>
 <clothing>
  <id>
   558854261
  </id>
  <name>
   Addidas T-shirt J-5261
  </name>
  <category>
   T-shirt
  </category>
  <size>
   XL
  </size>
  <color>
   Зеленый
  </color>
  <material>
   Лен
  </material>
  <price>
   192714
  </price>
  <rating>
   4.22
  </rating>
  <reviews>
   965809
  </reviews>
 </clothing>
 <clothing>
  <id>
   735292961
  </id>
  <name>
   Ellesse Sweater L-2551
  </name>
  <category>
   Sweater
  </category>
  <size>
   S
  </size>
  <color>
   Фиолетовый
  </color>
  <material>
   Хлопок
  </material>
  <price>
   583315
  </price>
  <rating>
   2.38
  </rating>
  <reviews>
   649094
  </reviews>
 </clothing>
 <clothing>
  <id>
   783639211
  </id>
  <name>
   Puma Pants A-9023
  </name>
  <category>
   Pants
  </category>
  <size>
   XL
  </size>
  <color>
   Красный
  </color>
  <material>
   Полиэстер
  </material>
  <price>
   914574
  </price>
  <rating>
   2.47
  </rating>
  <reviews>
   956697
  </reviews>
  <new>
   +
  </new>
  <exclusive>
   yes
  </exclusive>
 </clothing>
</clothing-items>
